antidb/__init__.py
antidb/err.py
antidb/idx.py
antidb/prs.py
antidb/srt.py
antidb-2025.4.4.dist-info/licenses/LICENSE
antidb-2025.4.4.dist-info/WHEEL
antidb-2025.4.4.dist-info/METADATA
antidb-2025.4.4.dist-info/RECORD
