Metadata-Version: 2.4
Name: antidb
Version: 2025.4.4
Summary: The simplest index-and-search engine for huge multiline text files. Focused primarily on bioinformatics. Inspired by tabix, but isn't its replacement. Written in Python. Works on top of Zstandard Seekable & pyzstd SeekableZstdFile.
Keywords: python,search-engine,parser,performance,bioinformatics,big-data,dbms,indexer,zstd,zstandard,seekable,pyzstd
Author-email: Platon Bykadorov <platon.work@gmail.com>
Requires-Python: >=3.12
Classifier: Programming Language :: Python :: 3
Classifier: License :: OSI Approved :: GNU General Public License v3 (GPLv3)
Classifier: Operating System :: POSIX :: Linux
License-File: LICENSE
Requires-Dist: pyzstd >=0.16.2
Project-URL: Bug Tracker, https://github.com/PlatonB/antidb/issues
Project-URL: Homepage, https://github.com/PlatonB/antidb
